ebird/dataset/data/__init__.py
ebird/dataset/data/admin.py
ebird/dataset/data/apps.py
ebird/dataset/data/loaders.py
ebird/dataset/data/locale/en/LC_MESSAGES/django.mo
ebird/dataset/data/locale/en/LC_MESSAGES/django.po
ebird/dataset/data/management/__init__.py
ebird/dataset/data/management/commands/__init__.py
ebird/dataset/data/management/commands/load_dataset.py
ebird/dataset/data/migrations/0001_initial.py
ebird/dataset/data/migrations/__init__.py
ebird/dataset/data/models/__init__.py
ebird/dataset/data/models/checklist.py
ebird/dataset/data/models/country.py
ebird/dataset/data/models/county.py
ebird/dataset/data/models/location.py
ebird/dataset/data/models/observation.py
ebird/dataset/data/models/observer.py
ebird/dataset/data/models/species.py
ebird/dataset/data/models/state.py
ebird_dataset_data-0.2.0.dist-info/METADATA
ebird_dataset_data-0.2.0.dist-info/WHEEL
ebird_dataset_data-0.2.0.dist-info/licenses/LICENSE
ebird_dataset_data-0.2.0.dist-info/RECORD
