Metadata-Version: 2.4
Name: ebird-dataset-data
Version: 0.2.0
Summary: eBird Dataset Data is a reusable Django app for loading data from the eBird Basic Dataset into a database.
Author-email: Stuart MacKay <smackay@flagstonesoftware.com>
License-Expression: MIT
License-File: LICENSE
Keywords: Django,checklists,eBird,eBird Basic Dataset,models,observations,species
Classifier: Development Status :: 4 - Beta
Classifier: Framework :: Django
Classifier: Framework :: Django :: 4.2
Classifier: Framework :: Django :: 5.0
Classifier: Framework :: Django :: 5.1
Classifier: Framework :: Django :: 5.2
Classifier: Intended Audience :: Science/Research
Classifier: Natural Language :: English
Classifier: Programming Language :: Python :: 3.10
Classifier: Programming Language :: Python :: 3.11
Classifier: Programming Language :: Python :: 3.12
Classifier: Programming Language :: Python :: 3.13
Classifier: Topic :: Scientific/Engineering
Classifier: Topic :: Scientific/Engineering :: Information Analysis
Requires-Python: >=3.12
Requires-Dist: django>=4.2
Requires-Dist: ebird-codes>=0.0.2
